[
  {
    "name": "Precious",
    "surname": "Achiuwa"
  },
  {
    "name": "Jaylen",
    "surname": "Adams"
  },
  {
    "name": "Steven",
    "surname": "Adams"
  },
  {
    "name": "Bam",
    "surname": "Adebayo"
  },
  {
    "name": "LaMarcus",
    "surname": "Aldridge"
  },
  {
    "name": "Ty-Shon",
    "surname": "Alexander"
  },
  {
    "name": "Nickeil",
    "surname": "Alexander-Walker"
  },
  {
    "name": "Grayson",
    "surname": "Allen"
  },
  {
    "name": "Jarrett",
    "surname": "Allen"
  },
  {
    "name": "Al-Farouq",
    "surname": "Aminu"
  },
  {
    "name": "Kyle",
    "surname": "Anderson"
  },
  {
    "name": "Giannis",
    "surname": "Antetokounmpo"
  },
  {
    "name": "Kostas",
    "surname": "Antetokounmpo"
  },
  {
    "name": "Thanasis",
    "surname": "Antetokounmpo"
  },
  {
    "name": "Carmelo",
    "surname": "Anthony"
  },
  {
    "name": "Cole",
    "surname": "Anthony"
  },
  {
    "name": "OG",
    "surname": "Anunoby"
  },
  {
    "name": "Ryan",
    "surname": "Arcidiacono"
  },
  {
    "name": "Trevor",
    "surname": "Ariza"
  },
  {
    "name": "D.J.",
    "surname": "Augustin"
  },
  {
    "name": "Deni",
    "surname": "Avdija"
  },
  {
    "name": "Deandre",
    "surname": "Ayton"
  },
  {
    "name": "Udoka",
    "surname": "Azubuike"
  },
  {
    "name": "Dwayne",
    "surname": "Bacon"
  },
  {
    "name": "Marvin",
    "surname": "Bagley III"
  },
  {
    "name": "LaMelo",
    "surname": "Ball"
  },
  {
    "name": "Lonzo",
    "surname": "Ball"
  },
  {
    "name": "Mo",
    "surname": "Bamba"
  },
  {
    "name": "Desmond",
    "surname": "Bane"
  },
  {
    "name": "Harrison",
    "surname": "Barnes"
  },
  {
    "name": "RJ",
    "surname": "Barrett"
  },
  {
    "name": "Will",
    "surname": "Barton"
  },
  {
    "name": "Keita",
    "surname": "Bates-Diop"
  },
  {
    "name": "Nicolas",
    "surname": "Batum"
  },
  {
    "name": "Aron",
    "surname": "Baynes"
  },
  {
    "name": "Kent",
    "surname": "Bazemore"
  },
  {
    "name": "Darius",
    "surname": "Bazley"
  },
  {
    "name": "Bradley",
    "surname": "Beal"
  },
  {
    "name": "Malik",
    "surname": "Beasley"
  },
  {
    "name": "Jordan",
    "surname": "Bell"
  },
  {
    "name": "DeAndre'",
    "surname": "Bembry"
  },
  {
    "name": "Davis",
    "surname": "Bertans"
  },
  {
    "name": "Patrick",
    "surname": "Beverley"
  },
  {
    "name": "Saddiq",
    "surname": "Bey"
  },
  {
    "name": "Tyler",
    "surname": "Bey"
  },
  {
    "name": "Khem",
    "surname": "Birch"
  },
  {
    "name": "Goga",
    "surname": "Bitadze"
  },
  {
    "name": "Bismack",
    "surname": "Biyombo"
  },
  {
    "name": "Nemanja",
    "surname": "Bjelica"
  },
  {
    "name": "Eric",
    "surname": "Bledsoe"
  },
  {
    "name": "Keljin",
    "surname": "Blevins"
  },
  {
    "name": "Bogdan",
    "surname": "Bogdanovic"
  },
  {
    "name": "Bojan",
    "surname": "Bogdanovic"
  },
  {
    "name": "Bol",
    "surname": "Bol"
  },
  {
    "name": "Marques",
    "surname": "Bolden"
  },
  {
    "name": "Jordan",
    "surname": "Bone"
  },
  {
    "name": "Isaac",
    "surname": "Bonga"
  },
  {
    "name": "Devin",
    "surname": "Booker"
  },
  {
    "name": "Chris",
    "surname": "Boucher"
  },
  {
    "name": "Brian",
    "surname": "Bowen II"
  },
  {
    "name": "Avery",
    "surname": "Bradley"
  },
  {
    "name": "Tony",
    "surname": "Bradley"
  },
  {
    "name": "Jarrell",
    "surname": "Brantley"
  },
  {
    "name": "Ignas",
    "surname": "Brazdeikis"
  },
  {
    "name": "Mikal",
    "surname": "Bridges"
  },
  {
    "name": "Miles",
    "surname": "Bridges"
  },
  {
    "name": "Amida",
    "surname": "Brimah"
  },
  {
    "name": "Oshae",
    "surname": "Brissett"
  },
  {
    "name": "Malcolm",
    "surname": "Brogdon"
  },
  {
    "name": "Armoni",
    "surname": "Brooks"
  },
  {
    "name": "Dillon",
    "surname": "Brooks"
  },
  {
    "name": "Bruce",
    "surname": "Brown"
  },
  {
    "name": "Jaylen",
    "surname": "Brown"
  },
  {
    "name": "Moses",
    "surname": "Brown"
  },
  {
    "name": "Sterling",
    "surname": "Brown"
  },
  {
    "name": "Charlie",
    "surname": "Brown Jr."
  },
  {
    "name": "Troy",
    "surname": "Brown Jr."
  },
  {
    "name": "Jalen",
    "surname": "Brunson"
  },
  {
    "name": "Elijah",
    "surname": "Bryant"
  },
  {
    "name": "Thomas",
    "surname": "Bryant"
  },
  {
    "name": "Reggie",
    "surname": "Bullock"
  },
  {
    "name": "Trey",
    "surname": "Burke"
  },
  {
    "name": "Alec",
    "surname": "Burks"
  },
  {
    "name": "Jimmy",
    "surname": "Butler"
  },
  {
    "name": "Bruno",
    "surname": "Caboclo"
  },
  {
    "name": "Devontae",
    "surname": "Cacok"
  },
  {
    "name": "Kentavious",
    "surname": "Caldwell-Pope"
  },
  {
    "name": "Facundo",
    "surname": "Campazzo"
  },
  {
    "name": "Vlatko",
    "surname": "Cancar"
  },
  {
    "name": "Devin",
    "surname": "Cannady"
  },
  {
    "name": "Clint",
    "surname": "Capela"
  },
  {
    "name": "Vernon",
    "surname": "Carey Jr."
  },
  {
    "name": "Jevon",
    "surname": "Carter"
  },
  {
    "name": "Wendell",
    "surname": "Carter Jr."
  },
  {
    "name": "Michael",
    "surname": "Carter-Williams"
  },
  {
    "name": "Alex",
    "surname": "Caruso"
  },
  {
    "name": "Willie",
    "surname": "Cauley-Stein"
  },
  {
    "name": "Chris",
    "surname": "Chiozza"
  },
  {
    "name": "Marquese",
    "surname": "Chriss"
  },
  {
    "name": "Gary",
    "surname": "Clark"
  },
  {
    "name": "Brandon",
    "surname": "Clarke"
  },
  {
    "name": "Jordan",
    "surname": "Clarkson"
  },
  {
    "name": "Nicolas",
    "surname": "Claxton"
  },
  {
    "name": "Amir",
    "surname": "Coffey"
  },
  {
    "name": "John",
    "surname": "Collins"
  },
  {
    "name": "Zach",
    "surname": "Collins"
  },
  {
    "name": "Mike",
    "surname": "Conley"
  },
  {
    "name": "Pat",
    "surname": "Connaughton"
  },
  {
    "name": "Quinn",
    "surname": "Cook"
  },
  {
    "name": "Tyler",
    "surname": "Cook"
  },
  {
    "name": "DeMarcus",
    "surname": "Cousins"
  },
  {
    "name": "Robert",
    "surname": "Covington"
  },
  {
    "name": "Torrey",
    "surname": "Craig"
  },
  {
    "name": "Jae",
    "surname": "Crowder"
  },
  {
    "name": "Jarrett",
    "surname": "Culver"
  },
  {
    "name": "Seth",
    "surname": "Curry"
  },
  {
    "name": "Stephen",
    "surname": "Curry"
  },
  {
    "name": "Nate",
    "surname": "Darling"
  },
  {
    "name": "Anthony",
    "surname": "Davis"
  },
  {
    "name": "Ed",
    "surname": "Davis"
  },
  {
    "name": "Terence",
    "surname": "Davis"
  },
  {
    "name": "DeMar",
    "surname": "DeRozan"
  },
  {
    "name": "Gabriel",
    "surname": "Deck"
  },
  {
    "name": "Dewayne",
    "surname": "Dedmon"
  },
  {
    "name": "Matthew",
    "surname": "Dellavedova"
  },
  {
    "name": "Donte",
    "surname": "DiVincenzo"
  },
  {
    "name": "Mamadi",
    "surname": "Diakite"
  },
  {
    "name": "Hamidou",
    "surname": "Diallo"
  },
  {
    "name": "Gorgui",
    "surname": "Dieng"
  },
  {
    "name": "Spencer",
    "surname": "Dinwiddie"
  },
  {
    "name": "Luka",
    "surname": "Doncic"
  },
  {
    "name": "Luguentz",
    "surname": "Dort"
  },
  {
    "name": "Damyean",
    "surname": "Dotson"
  },
  {
    "name": "Devon",
    "surname": "Dotson"
  },
  {
    "name": "Sekou",
    "surname": "Doumbouya"
  },
  {
    "name": "PJ",
    "surname": "Dozier"
  },
  {
    "name": "Goran",
    "surname": "Dragic"
  },
  {
    "name": "Andre",
    "surname": "Drummond"
  },
  {
    "name": "Jared",
    "surname": "Dudley"
  },
  {
    "name": "Kris",
    "surname": "Dunn"
  },
  {
    "name": "Kevin",
    "surname": "Durant"
  },
  {
    "name": "Anthony",
    "surname": "Edwards"
  },
  {
    "name": "Carsen",
    "surname": "Edwards"
  },
  {
    "name": "CJ",
    "surname": "Elleby"
  },
  {
    "name": "Henry",
    "surname": "Ellenson"
  },
  {
    "name": "Wayne",
    "surname": "Ellington"
  },
  {
    "name": "Joel",
    "surname": "Embiid"
  },
  {
    "name": "James",
    "surname": "Ennis III"
  },
  {
    "name": "Drew",
    "surname": "Eubanks"
  },
  {
    "name": "Dante",
    "surname": "Exum"
  },
  {
    "name": "Tacko",
    "surname": "Fall"
  },
  {
    "name": "Derrick",
    "surname": "Favors"
  },
  {
    "name": "Cristiano",
    "surname": "Felicio"
  },
  {
    "name": "Terrance",
    "surname": "Ferguson"
  },
  {
    "name": "Bruno",
    "surname": "Fernando"
  },
  {
    "name": "Yogi",
    "surname": "Ferrell"
  },
  {
    "name": "Dorian",
    "surname": "Finney-Smith"
  },
  {
    "name": "Malik",
    "surname": "Fitts"
  },
  {
    "name": "Malachi",
    "surname": "Flynn"
  },
  {
    "name": "Bryn",
    "surname": "Forbes"
  },
  {
    "name": "Trent",
    "surname": "Forrest"
  },
  {
    "name": "Evan",
    "surname": "Fournier"
  },
  {
    "name": "De'Aaron",
    "surname": "Fox"
  },
  {
    "name": "Robert",
    "surname": "Franks"
  },
  {
    "name": "Tim",
    "surname": "Frazier"
  },
  {
    "name": "Markelle",
    "surname": "Fultz"
  },
  {
    "name": "Wenyen",
    "surname": "Gabriel"
  },
  {
    "name": "Daniel",
    "surname": "Gafford"
  },
  {
    "name": "Danilo",
    "surname": "Gallinari"
  },
  {
    "name": "Langston",
    "surname": "Galloway"
  },
  {
    "name": "Darius",
    "surname": "Garland"
  },
  {
    "name": "Marc",
    "surname": "Gasol"
  },
  {
    "name": "Rudy",
    "surname": "Gay"
  },
  {
    "name": "Paul",
    "surname": "George"
  },
  {
    "name": "Taj",
    "surname": "Gibson"
  },
  {
    "name": "Harry",
    "surname": "Giles III"
  },
  {
    "name": "Shai",
    "surname": "Gilgeous-Alexander"
  },
  {
    "name": "Anthony",
    "surname": "Gill"
  },
  {
    "name": "Freddie",
    "surname": "Gillespie"
  },
  {
    "name": "Rudy",
    "surname": "Gobert"
  },
  {
    "name": "Brandon",
    "surname": "Goodwin"
  },
  {
    "name": "Aaron",
    "surname": "Gordon"
  },
  {
    "name": "Eric",
    "surname": "Gordon"
  },
  {
    "name": "Devonte'",
    "surname": "Graham"
  },
  {
    "name": "Jerami",
    "surname": "Grant"
  },
  {
    "name": "Danny",
    "surname": "Green"
  },
  {
    "name": "Draymond",
    "surname": "Green"
  },
  {
    "name": "JaMychal",
    "surname": "Green"
  },
  {
    "name": "Javonte",
    "surname": "Green"
  },
  {
    "name": "Jeff",
    "surname": "Green"
  },
  {
    "name": "Josh",
    "surname": "Green"
  },
  {
    "name": "Blake",
    "surname": "Griffin"
  },
  {
    "name": "Kyle",
    "surname": "Guy"
  },
  {
    "name": "Rui",
    "surname": "Hachimura"
  },
  {
    "name": "Ashton",
    "surname": "Hagans"
  },
  {
    "name": "Tyrese",
    "surname": "Haliburton"
  },
  {
    "name": "Donta",
    "surname": "Hall"
  },
  {
    "name": "Josh",
    "surname": "Hall"
  },
  {
    "name": "R.J.",
    "surname": "Hampton"
  },
  {
    "name": "Tim",
    "surname": "Hardaway Jr."
  },
  {
    "name": "James",
    "surname": "Harden"
  },
  {
    "name": "Maurice",
    "surname": "Harkless"
  },
  {
    "name": "Jared",
    "surname": "Harper"
  },
  {
    "name": "Montrezl",
    "surname": "Harrell"
  },
  {
    "name": "Gary",
    "surname": "Harris"
  },
  {
    "name": "Jalen",
    "surname": "Harris"
  },
  {
    "name": "Joe",
    "surname": "Harris"
  },
  {
    "name": "Tobias",
    "surname": "Harris"
  },
  {
    "name": "Shaquille",
    "surname": "Harrison"
  },
  {
    "name": "Josh",
    "surname": "Hart"
  },
  {
    "name": "Isaiah",
    "surname": "Hartenstein"
  },
  {
    "name": "Udonis",
    "surname": "Haslem"
  },
  {
    "name": "Jaxson",
    "surname": "Hayes"
  },
  {
    "name": "Killian",
    "surname": "Hayes"
  },
  {
    "name": "Gordon",
    "surname": "Hayward"
  },
  {
    "name": "Juancho",
    "surname": "Hernangomez"
  },
  {
    "name": "Willy",
    "surname": "Hernangomez"
  },
  {
    "name": "Tyler",
    "surname": "Herro"
  },
  {
    "name": "Buddy",
    "surname": "Hield"
  },
  {
    "name": "George",
    "surname": "Hill"
  },
  {
    "name": "Solomon",
    "surname": "Hill"
  },
  {
    "name": "Nate",
    "surname": "Hinton"
  },
  {
    "name": "Jaylen",
    "surname": "Hoard"
  },
  {
    "name": "Aaron",
    "surname": "Holiday"
  },
  {
    "name": "Jrue",
    "surname": "Holiday"
  },
  {
    "name": "Justin",
    "surname": "Holiday"
  },
  {
    "name": "Rondae",
    "surname": "Hollis-Jefferson"
  },
  {
    "name": "Richaun",
    "surname": "Holmes"
  },
  {
    "name": "Rodney",
    "surname": "Hood"
  },
  {
    "name": "Al",
    "surname": "Horford"
  },
  {
    "name": "Talen",
    "surname": "Horton-Tucker"
  },
  {
    "name": "Danuel",
    "surname": "House Jr."
  },
  {
    "name": "Dwight",
    "surname": "Howard"
  },
  {
    "name": "Markus",
    "surname": "Howard"
  },
  {
    "name": "Kevin",
    "surname": "Huerter"
  },
  {
    "name": "Elijah",
    "surname": "Hughes"
  },
  {
    "name": "De'Andre",
    "surname": "Hunter"
  },
  {
    "name": "Chandler",
    "surname": "Hutchison"
  },
  {
    "name": "Serge",
    "surname": "Ibaka"
  },
  {
    "name": "Andre",
    "surname": "Iguodala"
  },
  {
    "name": "Ersan",
    "surname": "Ilyasova"
  },
  {
    "name": "Joe",
    "surname": "Ingles"
  },
  {
    "name": "Brandon",
    "surname": "Ingram"
  },
  {
    "name": "Kyrie",
    "surname": "Irving"
  },
  {
    "name": "Jonathan",
    "surname": "Isaac"
  },
  {
    "name": "Wes",
    "surname": "Iwundu"
  },
  {
    "name": "Frank",
    "surname": "Jackson"
  },
  {
    "name": "Josh",
    "surname": "Jackson"
  },
  {
    "name": "Justin",
    "surname": "Jackson"
  },
  {
    "name": "Reggie",
    "surname": "Jackson"
  },
  {
    "name": "Jaren",
    "surname": "Jackson Jr."
  },
  {
    "name": "Justin",
    "surname": "James"
  },
  {
    "name": "LeBron",
    "surname": "James"
  },
  {
    "name": "Mike",
    "surname": "James"
  },
  {
    "name": "DaQuan",
    "surname": "Jeffries"
  },
  {
    "name": "Ty",
    "surname": "Jerome"
  },
  {
    "name": "Isaiah",
    "surname": "Joe"
  },
  {
    "name": "Alize",
    "surname": "Johnson"
  },
  {
    "name": "Cameron",
    "surname": "Johnson"
  },
  {
    "name": "James",
    "surname": "Johnson"
  },
  {
    "name": "Keldon",
    "surname": "Johnson"
  },
  {
    "name": "Stanley",
    "surname": "Johnson"
  },
  {
    "name": "Tyler",
    "surname": "Johnson"
  },
  {
    "name": "Nikola",
    "surname": "Jokic"
  },
  {
    "name": "Damian",
    "surname": "Jones"
  },
  {
    "name": "Mason",
    "surname": "Jones"
  },
  {
    "name": "Tre",
    "surname": "Jones"
  },
  {
    "name": "Tyus",
    "surname": "Jones"
  },
  {
    "name": "Derrick",
    "surname": "Jones Jr."
  },
  {
    "name": "DeAndre",
    "surname": "Jordan"
  },
  {
    "name": "Cory",
    "surname": "Joseph"
  },
  {
    "name": "Mfiondu",
    "surname": "Kabengele"
  },
  {
    "name": "Frank",
    "surname": "Kaminsky"
  },
  {
    "name": "Enes",
    "surname": "Kanter"
  },
  {
    "name": "Luke",
    "surname": "Kennard"
  },
  {
    "name": "Louis",
    "surname": "King"
  },
  {
    "name": "Maxi",
    "surname": "Kleber"
  },
  {
    "name": "Nathan",
    "surname": "Knight"
  },
  {
    "name": "Kevin",
    "surname": "Knox II"
  },
  {
    "name": "John",
    "surname": "Konchar"
  },
  {
    "name": "Furkan",
    "surname": "Korkmaz"
  },
  {
    "name": "Luke",
    "surname": "Kornet"
  },
  {
    "name": "Rodions",
    "surname": "Kurucs"
  },
  {
    "name": "Kyle",
    "surname": "Kuzma"
  },
  {
    "name": "Zach",
    "surname": "LaVine"
  },
  {
    "name": "Anthony",
    "surname": "Lamb"
  },
  {
    "name": "Jeremy",
    "surname": "Lamb"
  },
  {
    "name": "Romeo",
    "surname": "Langford"
  },
  {
    "name": "Jake",
    "surname": "Layman"
  },
  {
    "name": "Caris",
    "surname": "LeVert"
  },
  {
    "name": "T.J.",
    "surname": "Leaf"
  },
  {
    "name": "Jalen",
    "surname": "Lecque"
  },
  {
    "name": "Damion",
    "surname": "Lee"
  },
  {
    "name": "Saben",
    "surname": "Lee"
  },
  {
    "name": "Alex",
    "surname": "Len"
  },
  {
    "name": "Kawhi",
    "surname": "Leonard"
  },
  {
    "name": "Meyers",
    "surname": "Leonard"
  },
  {
    "name": "Kira",
    "surname": "Lewis Jr."
  },
  {
    "name": "Damian",
    "surname": "Lillard"
  },
  {
    "name": "Nassir",
    "surname": "Little"
  },
  {
    "name": "Kevon",
    "surname": "Looney"
  },
  {
    "name": "Brook",
    "surname": "Lopez"
  },
  {
    "name": "Robin",
    "surname": "Lopez"
  },
  {
    "name": "Didi",
    "surname": "Louzada"
  },
  {
    "name": "Kevin",
    "surname": "Love"
  },
  {
    "name": "Kyle",
    "surname": "Lowry"
  },
  {
    "name": "Timothe",
    "surname": "Luwawu-Cabarrot"
  },
  {
    "name": "Trey",
    "surname": "Lyles"
  },
  {
    "name": "Will",
    "surname": "Magnay"
  },
  {
    "name": "Thon",
    "surname": "Maker"
  },
  {
    "name": "Theo",
    "surname": "Maledon"
  },
  {
    "name": "Karim",
    "surname": "Mane"
  },
  {
    "name": "Terance",
    "surname": "Mann"
  },
  {
    "name": "Nico",
    "surname": "Mannion"
  },
  {
    "name": "Boban",
    "surname": "Marjanovic"
  },
  {
    "name": "Lauri",
    "surname": "Markkanen"
  },
  {
    "name": "Naji",
    "surname": "Marshall"
  },
  {
    "name": "Caleb",
    "surname": "Martin"
  },
  {
    "name": "Cody",
    "surname": "Martin"
  },
  {
    "name": "Jeremiah",
    "surname": "Martin"
  },
  {
    "name": "Kelan",
    "surname": "Martin"
  },
  {
    "name": "Kenyon",
    "surname": "Martin Jr."
  },
  {
    "name": "Frank",
    "surname": "Mason"
  },
  {
    "name": "Garrison",
    "surname": "Mathews"
  },
  {
    "name": "Dakota",
    "surname": "Mathias"
  },
  {
    "name": "Wesley",
    "surname": "Matthews"
  },
  {
    "name": "Tyrese",
    "surname": "Maxey"
  },
  {
    "name": "Skylar",
    "surname": "Mays"
  },
  {
    "name": "Patrick",
    "surname": "McCaw"
  },
  {
    "name": "CJ",
    "surname": "McCollum"
  },
  {
    "name": "T.J.",
    "surname": "McConnell"
  },
  {
    "name": "Jaden",
    "surname": "McDaniels"
  },
  {
    "name": "Jalen",
    "surname": "McDaniels"
  },
  {
    "name": "Doug",
    "surname": "McDermott"
  },
  {
    "name": "Sean",
    "surname": "McDermott"
  },
  {
    "name": "JaVale",
    "surname": "McGee"
  },
  {
    "name": "Rodney",
    "surname": "McGruder"
  },
  {
    "name": "Alfonzo",
    "surname": "McKinnie"
  },
  {
    "name": "Jordan",
    "surname": "McLaughlin"
  },
  {
    "name": "Ben",
    "surname": "McLemore"
  },
  {
    "name": "Nicolo",
    "surname": "Melli"
  },
  {
    "name": "De'Anthony",
    "surname": "Melton"
  },
  {
    "name": "Sam",
    "surname": "Merrill"
  },
  {
    "name": "Chimezie",
    "surname": "Metu"
  },
  {
    "name": "Khris",
    "surname": "Middleton"
  },
  {
    "name": "Darius",
    "surname": "Miller"
  },
  {
    "name": "Patty",
    "surname": "Mills"
  },
  {
    "name": "Paul",
    "surname": "Millsap"
  },
  {
    "name": "Shake",
    "surname": "Milton"
  },
  {
    "name": "Donovan",
    "surname": "Mitchell"
  },
  {
    "name": "Adam",
    "surname": "Mokoka"
  },
  {
    "name": "Malik",
    "surname": "Monk"
  },
  {
    "name": "E'Twaun",
    "surname": "Moore"
  },
  {
    "name": "Ja",
    "surname": "Morant"
  },
  {
    "name": "Juwan",
    "surname": "Morgan"
  },
  {
    "name": "Markieff",
    "surname": "Morris"
  },
  {
    "name": "Monte",
    "surname": "Morris"
  },
  {
    "name": "Marcus",
    "surname": "Morris Sr."
  },
  {
    "name": "Mychal",
    "surname": "Mulder"
  },
  {
    "name": "Dejounte",
    "surname": "Murray"
  },
  {
    "name": "Jamal",
    "surname": "Murray"
  },
  {
    "name": "Mike",
    "surname": "Muscala"
  },
  {
    "name": "Svi",
    "surname": "Mykhailiuk"
  },
  {
    "name": "Abdel",
    "surname": "Nader"
  },
  {
    "name": "Larry",
    "surname": "Nance Jr."
  },
  {
    "name": "Aaron",
    "surname": "Nesmith"
  },
  {
    "name": "Raul",
    "surname": "Neto"
  },
  {
    "name": "Georges",
    "surname": "Niang"
  },
  {
    "name": "Zeke",
    "surname": "Nnaji"
  },
  {
    "name": "Nerlens",
    "surname": "Noel"
  },
  {
    "name": "Jaylen",
    "surname": "Nowell"
  },
  {
    "name": "Frank",
    "surname": "Ntilikina"
  },
  {
    "name": "Kendrick",
    "surname": "Nunn"
  },
  {
    "name": "James",
    "surname": "Nunnally"
  },
  {
    "name": "Jusuf",
    "surname": "Nurkic"
  },
  {
    "name": "David",
    "surname": "Nwaba"
  },
  {
    "name": "Jordan",
    "surname": "Nwora"
  },
  {
    "name": "Royce",
    "surname": "O'Neale"
  },
  {
    "name": "Semi",
    "surname": "Ojeleye"
  },
  {
    "name": "Jahlil",
    "surname": "Okafor"
  },
  {
    "name": "Chuma",
    "surname": "Okeke"
  },
  {
    "name": "Josh",
    "surname": "Okogie"
  },
  {
    "name": "Onyeka",
    "surname": "Okongwu"
  },
  {
    "name": "Isaac",
    "surname": "Okoro"
  },
  {
    "name": "KZ",
    "surname": "Okpala"
  },
  {
    "name": "Victor",
    "surname": "Oladipo"
  },
  {
    "name": "Cameron",
    "surname": "Oliver"
  },
  {
    "name": "Kelly",
    "surname": "Olynyk"
  },
  {
    "name": "Miye",
    "surname": "Oni"
  },
  {
    "name": "Cedi",
    "surname": "Osman"
  },
  {
    "name": "Daniel",
    "surname": "Oturu"
  },
  {
    "name": "Kelly",
    "surname": "Oubre Jr."
  },
  {
    "name": "Jabari",
    "surname": "Parker"
  },
  {
    "name": "Eric",
    "surname": "Paschall"
  },
  {
    "name": "Anzejs",
    "surname": "Pasecniks"
  },
  {
    "name": "Patrick",
    "surname": "Patterson"
  },
  {
    "name": "Justin",
    "surname": "Patton"
  },
  {
    "name": "Chris",
    "surname": "Paul"
  },
  {
    "name": "Cameron",
    "surname": "Payne"
  },
  {
    "name": "Elfrid",
    "surname": "Payton"
  },
  {
    "name": "Gary",
    "surname": "Payton II"
  },
  {
    "name": "Norvel",
    "surname": "Pelle"
  },
  {
    "name": "Reggie",
    "surname": "Perry"
  },
  {
    "name": "Theo",
    "surname": "Pinson"
  },
  {
    "name": "Mason",
    "surname": "Plumlee"
  },
  {
    "name": "Jakob",
    "surname": "Poeltl"
  },
  {
    "name": "Vincent",
    "surname": "Poirier"
  },
  {
    "name": "Aleksej",
    "surname": "Pokusevski"
  },
  {
    "name": "Jordan",
    "surname": "Poole"
  },
  {
    "name": "Jontay",
    "surname": "Porter"
  },
  {
    "name": "Kevin",
    "surname": "Porter Jr."
  },
  {
    "name": "Michael",
    "surname": "Porter Jr."
  },
  {
    "name": "Otto",
    "surname": "Porter Jr."
  },
  {
    "name": "Bobby",
    "surname": "Portis"
  },
  {
    "name": "Kristaps",
    "surname": "Porzingis"
  },
  {
    "name": "Dwight",
    "surname": "Powell"
  },
  {
    "name": "Norman",
    "surname": "Powell"
  },
  {
    "name": "Taurean",
    "surname": "Prince"
  },
  {
    "name": "Payton",
    "surname": "Pritchard"
  },
  {
    "name": "Immanuel",
    "surname": "Quickley"
  },
  {
    "name": "Jahmi'us",
    "surname": "Ramsey"
  },
  {
    "name": "Chasson",
    "surname": "Randle"
  },
  {
    "name": "Julius",
    "surname": "Randle"
  },
  {
    "name": "Cam",
    "surname": "Reddish"
  },
  {
    "name": "JJ",
    "surname": "Redick"
  },
  {
    "name": "Paul",
    "surname": "Reed"
  },
  {
    "name": "Naz",
    "surname": "Reid"
  },
  {
    "name": "Cameron",
    "surname": "Reynolds"
  },
  {
    "name": "Nick",
    "surname": "Richards"
  },
  {
    "name": "Josh",
    "surname": "Richardson"
  },
  {
    "name": "Grant",
    "surname": "Riller"
  },
  {
    "name": "Austin",
    "surname": "Rivers"
  },
  {
    "name": "Andre",
    "surname": "Roberson"
  },
  {
    "name": "Duncan",
    "surname": "Robinson"
  },
  {
    "name": "Jerome",
    "surname": "Robinson"
  },
  {
    "name": "Justin",
    "surname": "Robinson"
  },
  {
    "name": "Mitchell",
    "surname": "Robinson"
  },
  {
    "name": "Glenn",
    "surname": "Robinson III"
  },
  {
    "name": "Isaiah",
    "surname": "Roby"
  },
  {
    "name": "Rajon",
    "surname": "Rondo"
  },
  {
    "name": "Derrick",
    "surname": "Rose"
  },
  {
    "name": "Terrence",
    "surname": "Ross"
  },
  {
    "name": "Terry",
    "surname": "Rozier"
  },
  {
    "name": "Ricky",
    "surname": "Rubio"
  },
  {
    "name": "D'Angelo",
    "surname": "Russell"
  },
  {
    "name": "Domantas",
    "surname": "Sabonis"
  },
  {
    "name": "Luka",
    "surname": "Samanic"
  },
  {
    "name": "JaKarr",
    "surname": "Sampson"
  },
  {
    "name": "Dario",
    "surname": "Saric"
  },
  {
    "name": "Tomas",
    "surname": "Satoransky"
  },
  {
    "name": "Dennis",
    "surname": "Schroder"
  },
  {
    "name": "Mike",
    "surname": "Scott"
  },
  {
    "name": "Jay",
    "surname": "Scrubb"
  },
  {
    "name": "Collin",
    "surname": "Sexton"
  },
  {
    "name": "Landry",
    "surname": "Shamet"
  },
  {
    "name": "Iman",
    "surname": "Shumpert"
  },
  {
    "name": "Pascal",
    "surname": "Siakam"
  },
  {
    "name": "Chris",
    "surname": "Silva"
  },
  {
    "name": "Ben",
    "surname": "Simmons"
  },
  {
    "name": "Anfernee",
    "surname": "Simons"
  },
  {
    "name": "Deividas",
    "surname": "Sirvydis"
  },
  {
    "name": "Alen",
    "surname": "Smailagic"
  },
  {
    "name": "Marcus",
    "surname": "Smart"
  },
  {
    "name": "Ish",
    "surname": "Smith"
  },
  {
    "name": "Jalen",
    "surname": "Smith"
  },
  {
    "name": "Dennis",
    "surname": "Smith Jr."
  },
  {
    "name": "Tony",
    "surname": "Snell"
  },
  {
    "name": "Ray",
    "surname": "Spalding"
  },
  {
    "name": "Cassius",
    "surname": "Stanley"
  },
  {
    "name": "Lamar",
    "surname": "Stevens"
  },
  {
    "name": "Isaiah",
    "surname": "Stewart"
  },
  {
    "name": "Max",
    "surname": "Strus"
  },
  {
    "name": "Edmond",
    "surname": "Sumner"
  },
  {
    "name": "Jae'Sean",
    "surname": "Tate"
  },
  {
    "name": "Jayson",
    "surname": "Tatum"
  },
  {
    "name": "Jeff",
    "surname": "Teague"
  },
  {
    "name": "Garrett",
    "surname": "Temple"
  },
  {
    "name": "Tyrell",
    "surname": "Terry"
  },
  {
    "name": "Daniel",
    "surname": "Theis"
  },
  {
    "name": "Brodric",
    "surname": "Thomas"
  },
  {
    "name": "Isaiah",
    "surname": "Thomas"
  },
  {
    "name": "Khyri",
    "surname": "Thomas"
  },
  {
    "name": "Matt",
    "surname": "Thomas"
  },
  {
    "name": "Klay",
    "surname": "Thompson"
  },
  {
    "name": "Tristan",
    "surname": "Thompson"
  },
  {
    "name": "Sindarius",
    "surname": "Thornwell"
  },
  {
    "name": "Matisse",
    "surname": "Thybulle"
  },
  {
    "name": "Killian",
    "surname": "Tillie"
  },
  {
    "name": "Xavier",
    "surname": "Tillman"
  },
  {
    "name": "Anthony",
    "surname": "Tolliver"
  },
  {
    "name": "Obi",
    "surname": "Toppin"
  },
  {
    "name": "Juan",
    "surname": "Toscano-Anderson"
  },
  {
    "name": "Axel",
    "surname": "Toupane"
  },
  {
    "name": "Karl-Anthony",
    "surname": "Towns"
  },
  {
    "name": "Gary",
    "surname": "Trent Jr."
  },
  {
    "name": "P.J.",
    "surname": "Tucker"
  },
  {
    "name": "Rayjon",
    "surname": "Tucker"
  },
  {
    "name": "Myles",
    "surname": "Turner"
  },
  {
    "name": "Jonas",
    "surname": "Valanciunas"
  },
  {
    "name": "Denzel",
    "surname": "Valentine"
  },
  {
    "name": "Fred",
    "surname": "VanVleet"
  },
  {
    "name": "Jarred",
    "surname": "Vanderbilt"
  },
  {
    "name": "Anderson",
    "surname": "Varejao"
  },
  {
    "name": "Devin",
    "surname": "Vassell"
  },
  {
    "name": "Luca",
    "surname": "Vildoza"
  },
  {
    "name": "Gabe",
    "surname": "Vincent"
  },
  {
    "name": "Noah",
    "surname": "Vonleh"
  },
  {
    "name": "Nikola",
    "surname": "Vucevic"
  },
  {
    "name": "Dean",
    "surname": "Wade"
  },
  {
    "name": "Moritz",
    "surname": "Wagner"
  },
  {
    "name": "Kemba",
    "surname": "Walker"
  },
  {
    "name": "Lonnie",
    "surname": "Walker IV"
  },
  {
    "name": "John",
    "surname": "Wall"
  },
  {
    "name": "Brad",
    "surname": "Wanamaker"
  },
  {
    "name": "T.J.",
    "surname": "Warren"
  },
  {
    "name": "P.J.",
    "surname": "Washington"
  },
  {
    "name": "Yuta",
    "surname": "Watanabe"
  },
  {
    "name": "Tremont",
    "surname": "Waters"
  },
  {
    "name": "Paul",
    "surname": "Watson"
  },
  {
    "name": "Quinndary",
    "surname": "Weatherspoon"
  },
  {
    "name": "Russell",
    "surname": "Westbrook"
  },
  {
    "name": "Coby",
    "surname": "White"
  },
  {
    "name": "Derrick",
    "surname": "White"
  },
  {
    "name": "Hassan",
    "surname": "Whiteside"
  },
  {
    "name": "Greg",
    "surname": "Whittington"
  },
  {
    "name": "Andrew",
    "surname": "Wiggins"
  },
  {
    "name": "Grant",
    "surname": "Williams"
  },
  {
    "name": "Kenrich",
    "surname": "Williams"
  },
  {
    "name": "Lou",
    "surname": "Williams"
  },
  {
    "name": "Patrick",
    "surname": "Williams"
  },
  {
    "name": "Robert",
    "surname": "Williams III"
  },
  {
    "name": "Zion",
    "surname": "Williamson"
  },
  {
    "name": "D.J.",
    "surname": "Wilson"
  },
  {
    "name": "Dylan",
    "surname": "Windler"
  },
  {
    "name": "Justise",
    "surname": "Winslow"
  },
  {
    "name": "Cassius",
    "surname": "Winston"
  },
  {
    "name": "James",
    "surname": "Wiseman"
  },
  {
    "name": "Christian",
    "surname": "Wood"
  },
  {
    "name": "Robert",
    "surname": "Woodard II"
  },
  {
    "name": "Delon",
    "surname": "Wright"
  },
  {
    "name": "Thaddeus",
    "surname": "Young"
  },
  {
    "name": "Trae",
    "surname": "Young"
  },
  {
    "name": "Omer",
    "surname": "Yurtseven"
  },
  {
    "name": "Cody",
    "surname": "Zeller"
  },
  {
    "name": "Ivica",
    "surname": "Zubac"
  }
]
